rtx50_compat.py
rtx50_compat-3.0.2.dist-info/licenses/LICENSE
rtx50_compat-3.0.2.dist-info/METADATA
rtx50_compat-3.0.2.dist-info/WHEEL
rtx50_compat-3.0.2.dist-info/top_level.txt
rtx50_compat-3.0.2.dist-info/RECORD
