Metadata-Version: 2.4
Name: rtx50-compat
Version: 3.0.2
Summary: RTX 50-series GPU compatibility layer for PyTorch and CUDA - enables sm_120 support
Home-page: https://github.com/jw/rtx50-compat
Author: JW
Author-email: JW <jw@diablogato.com>
License: MIT License
Project-URL: Homepage, https://github.com/jw/rtx50-compat
Project-URL: Bug Tracker, https://github.com/jw/rtx50-compat/issues
Classifier: Development Status :: 4 - Beta
Classifier: Intended Audience :: Developers
Classifier: Topic :: Scientific/Engineering :: Artificial Intelligence
Classifier: License :: OSI Approved :: MIT License
Classifier: Programming Language :: Python :: 3
Classifier: Programming Language :: Python :: 3.8
Classifier: Programming Language :: Python :: 3.9
Classifier: Programming Language :: Python :: 3.10
Classifier: Programming Language :: Python :: 3.11
Classifier: Programming Language :: Python :: 3.12
Requires-Python: >=3.8
License-File: LICENSE
Provides-Extra: dev
Requires-Dist: build; extra == "dev"
Requires-Dist: twine; extra == "dev"
Dynamic: author
Dynamic: home-page
Dynamic: license-file
Dynamic: requires-python
